py_grafana/__init__.py
py_grafana/base.py
py_grafana/baseAPI.py
py_grafana/connection.py
py_grafana/errors.py
py_grafana/token.py
py_grafana/grafana/__init__.py
py_grafana/grafana/grafana.py
py_grafana/grafana/admin/Admin.py
py_grafana/grafana/admin/__init__.py
py_grafana/grafana/authentication/Authentication.py
py_grafana/grafana/authentication/__init__.py
py_grafana/grafana/dashboard/Dashboard.py
py_grafana/grafana/dashboard/__init__.py
py_grafana/grafana/dashboard/panel/Panel.py
py_grafana/grafana/dashboard/panel/__init__.py
py_grafana/grafana/dashboard/panel/timeseries/TimeSeries.py
py_grafana/grafana/dashboard/panel/timeseries/__init__.py
py_grafana/grafana/datasource/DataSource.py
py_grafana/grafana/datasource/DataSourceAPI.py
py_grafana/grafana/datasource/__init__.py
py_grafana/grafana/datasource/DocumentAndLogging/DocumentAndLogging.py
py_grafana/grafana/datasource/DocumentAndLogging/__init__.py
py_grafana/grafana/datasource/SQL/SQL.py
py_grafana/grafana/datasource/SQL/__init__.py
py_grafana/grafana/datasource/TimeSeries/TimeSeries.py
py_grafana/grafana/datasource/TimeSeries/__init__.py
py_grafana/grafana/folder/Folder.py
py_grafana/grafana/folder/__init__.py
py_grafana/grafana/organization/Organization.py
py_grafana/grafana/organization/__init__.py
py_grafana/grafana/team/Team.py
py_grafana/grafana/team/__init__.py
py_grafana/grafana/users/User.py
py_grafana/grafana/users/__init__.py
py_grafana_sdk-0.0.1a0.dist-info/METADATA
py_grafana_sdk-0.0.1a0.dist-info/WHEEL
py_grafana_sdk-0.0.1a0.dist-info/top_level.txt
py_grafana_sdk-0.0.1a0.dist-info/RECORD
