Metadata-Version: 2.1
Name: py-grafana-sdk
Version: 0.0.1a0
Summary: A Library to Configure Grafana Using Rest
Home-page: https://github.com/harshsikhwal/py-grafana
Author: Vibaswan Roychowdhury & Harsh Sikhwal
Author-email: vroychowdhury@gmail.com
License: MIT
Keywords: grafana grafana-api grafana-sdk sdk api automation
Classifier: Development Status :: 2 - Pre-Alpha
Classifier: Intended Audience :: Developers
Classifier: Topic :: Software Development
Classifier: License :: OSI Approved :: MIT License
Classifier: Programming Language :: Python :: 3
Requires-Python: >=3.7, <4
Requires-Dist: requests
